setup.py
django_pipe2db.egg-info/PKG-INFO
django_pipe2db.egg-info/SOURCES.txt
django_pipe2db.egg-info/dependency_links.txt
django_pipe2db.egg-info/requires.txt
django_pipe2db.egg-info/top_level.txt
pipe2db/__init__.py
pipe2db/core.py
pipe2db/decorators.py
pipe2db/utils.py
pipe2db/vars.py
pipe2db/__pycache__/__init__.cpython-310.pyc
pipe2db/__pycache__/__init__.cpython-38.pyc
pipe2db/__pycache__/core.cpython-310.pyc
pipe2db/__pycache__/core.cpython-38.pyc
pipe2db/__pycache__/decorators.cpython-310.pyc
pipe2db/__pycache__/decorators.cpython-38.pyc
pipe2db/__pycache__/utils.cpython-310.pyc
pipe2db/__pycache__/utils.cpython-38.pyc
pipe2db/__pycache__/vars.cpython-310.pyc
pipe2db/__pycache__/vars.cpython-38.pyc
test/bookstore/__init__.py
test/bookstore/insert.py