Metadata-Version: 2.1
Name: django-pipe2db
Version: 0.0.6
Summary: A pipeline library that connects data generated by Python functions to Django models.
Home-page: https://github.com/zwolf21/django-pipe2db
Author: HS Moon
Author-email: pbr112@naver.com
License: MIT
Keywords: django pipeline pipe2db,standalone db
Platform: UNKNOWN
Classifier: Programming Language :: Python :: 3.7
Classifier: Programming Language :: Python :: 3.8
Classifier: Programming Language :: Python :: 3.9
Classifier: Programming Language :: Python :: 3.10
Provides-Extra: dev
Provides-Extra: test
